{
	"name": "BossFast",
	"plugin-id": "Sprite",
	"sid": 113047857453404,
	"isGlobal": false,
	"instanceVariables": [
		{
			"name": "damage",
			"type": "number",
			"desc": "number of hits taken",
			"show": true,
			"sid": 537386444952881
		}
	],
	"behaviorTypes": [
		{
			"behaviorId": "Bullet",
			"name": "Bullet",
			"sid": 706544050836060
		},
		{
			"behaviorId": "Timer",
			"name": "Timer",
			"sid": 173232913463926
		}
	],
	"effectTypes": [],
	"animations": {
		"items": [
			{
				"frames": [
					{
						"width": 256,
						"height": 256,
						"originX": 0.5,
						"originY": 0.5,
						"originalSource": "",
						"exportFormat": "lossless",
						"exportQuality": 0.8,
						"imageSpriteId": 2231178,
						"collisionPoly": {
							"points": [
								0.3333333333333333,
								0,
								0.6666666666666666,
								0,
								0.8,
								0.06666666666666667,
								0.9333333333333333,
								0.2,
								1,
								0.3333333333333333,
								1,
								0.6666666666666666,
								0.9333333333333333,
								0.8,
								0.8,
								0.9333333333333333,
								0.6666666666666666,
								1,
								0.3333333333333333,
								1,
								0.2,
								0.9333333333333333,
								0.06666666666666667,
								0.8,
								0,
								0.6666666666666666,
								0,
								0.3333333333333333,
								0.06666666666666667,
								0.2,
								0.2,
								0.06666666666666667
							]
						},
						"useCollisionPoly": true,
						"duration": 1,
						"tag": "enemy_normal"
					},
					{
						"width": 15,
						"height": 15,
						"originX": 0.5,
						"originY": 0.5,
						"originalSource": "",
						"exportFormat": "lossless",
						"exportQuality": 0.8,
						"imageSpriteId": 7529114,
						"useCollisionPoly": true,
						"duration": 1,
						"tag": "wide_shot"
					},
					{
						"width": 15,
						"height": 15,
						"originX": 0.5,
						"originY": 0.5,
						"originalSource": "",
						"exportFormat": "lossless",
						"exportQuality": 0.8,
						"imageSpriteId": 4950630,
						"useCollisionPoly": true,
						"duration": 1,
						"tag": "rapid_shot"
					},
					{
						"width": 15,
						"height": 15,
						"originX": 0.5,
						"originY": 0.5,
						"originalSource": "",
						"exportFormat": "lossless",
						"exportQuality": 0.8,
						"imageSpriteId": 8565458,
						"useCollisionPoly": true,
						"duration": 1,
						"tag": "rapid_shot"
					},
					{
						"width": 15,
						"height": 15,
						"originX": 0.5,
						"originY": 0.5,
						"originalSource": "",
						"exportFormat": "lossless",
						"exportQuality": 0.8,
						"imageSpriteId": 5147019,
						"useCollisionPoly": true,
						"duration": 1,
						"tag": "rapid_shot"
					},
					{
						"width": 15,
						"height": 15,
						"originX": 0.5,
						"originY": 0.5,
						"originalSource": "",
						"exportFormat": "lossless",
						"exportQuality": 0.8,
						"imageSpriteId": 4881887,
						"useCollisionPoly": true,
						"duration": 1,
						"tag": "rapid_shot"
					}
				],
				"sid": 422628780931655,
				"name": "Animation 1",
				"isLooping": false,
				"isPingPong": false,
				"repeatCount": 1,
				"repeatTo": 0,
				"speed": 0
			}
		],
		"subfolders": []
	}
}